bb/__init__.py
bb/util.py
bb/lib/darwin_amd64/bb
bb/lib/linux_386/bb
bb_python-0.1.3.dist-info/METADATA
bb_python-0.1.3.dist-info/WHEEL
bb_python-0.1.3.dist-info/top_level.txt
bb_python-0.1.3.dist-info/RECORD
