Metadata-Version: 2.1
Name: bb-python
Version: 0.1.3
Summary: bb Python Client
Home-page: https://mattsimmons1.github.io/bb
Author: Matt Simmons
Author-email: 
License: MIT
Platform: UNKNOWN
Classifier: License :: OSI Approved :: MIT License
Classifier: Programming Language :: Python :: 3
Classifier: Programming Language :: Python :: 3.7
Classifier: Programming Language :: Python :: 3.9
